{"cameraMode":{"drawMode":0,"name":"Shaded","section":"Shading Mode"},"sceneLighting":true,"audioPlay":false,"sceneViewState":{"m_AlwaysRefresh":false,"showFog":true,"showSkybox":true,"showFlares":true,"showImageEffects":true,"showParticleSystems":true,"showVisualEffectGraphs":true,"m_FxEnabled":true},"in2DMode":false,"pivot":{"x":2.2915477752685549,"y":0.19849348068237306,"z":-4.799088478088379},"rotation":{"x":-0.04882634058594704,"y":-0.9418464303016663,"z":0.1568298637866974,"w":-0.29321247339248659},"size":10.62678337097168,"orthographic":false}